cocina/__init__.py
cocina/cli.py
cocina/config_handler.py
cocina/constants.py
cocina/printer.py
cocina/utils.py
cocina-0.0.5.dist-info/licenses/LICENSE.md
cocina-0.0.5.dist-info/METADATA
cocina-0.0.5.dist-info/WHEEL
cocina-0.0.5.dist-info/entry_points.txt
cocina-0.0.5.dist-info/top_level.txt
cocina-0.0.5.dist-info/RECORD
