Metadata-Version: 2.4
Name: cocina
Version: 0.0.5
Summary: A collection of tools for building structured Python projects
Author-email: Brookie Guzder-Williams <bguzder-williams@berkeley.edu>
License: BSd 3-clause
Classifier: Development Status :: 4 - Beta
Classifier: Intended Audience :: Developers
Classifier: Programming Language :: Python :: 3
Classifier: Programming Language :: Python :: 3.8
Classifier: Programming Language :: Python :: 3.9
Classifier: Programming Language :: Python :: 3.10
Classifier: Programming Language :: Python :: 3.11
Classifier: Programming Language :: Python :: 3.12
Classifier: Topic :: Software Development :: Libraries
Classifier: Topic :: Scientific/Engineering
Requires-Python: >=3.11
License-File: LICENSE.md
Requires-Dist: pyyaml
Requires-Dist: click<9,>=8.2.1
Dynamic: license-file
